sensingcluespy/__init__.py
sensingcluespy/api_calls.py
sensingcluespy/sclogging.py
sensingcluespy/src/__init__.py
sensingcluespy/src/data_cleaner.py
sensingcluespy/src/data_extractor.py
sensingcluespy/src/exceptions.py
sensingcluespy/src/helper_functions.py
sensingcluespy-0.2.3.dist-info/LICENSE
sensingcluespy-0.2.3.dist-info/METADATA
sensingcluespy-0.2.3.dist-info/WHEEL
sensingcluespy-0.2.3.dist-info/top_level.txt
sensingcluespy-0.2.3.dist-info/RECORD
